LICENSE
MANIFEST.in
README.md
requirements.txt
setup.cfg
setup.py
bin/pyiridium.py
bin/pyiridium_server.py
docs/Makefile
docs/conf.py
docs/index.rst
docs/make.bat
pyiridium9602/__init__.py
pyiridium9602/__main__.py
pyiridium9602/__meta__.py
pyiridium9602/pyiridium.py
pyiridium9602/pyiridium_server.py
pyiridium9602.egg-info/PKG-INFO
pyiridium9602.egg-info/SOURCES.txt
pyiridium9602.egg-info/dependency_links.txt
pyiridium9602.egg-info/requires.txt
pyiridium9602.egg-info/top_level.txt
tests/simple_example.py
tests/test_custom_signal.py
tests/test_pyiridium.py