Metadata-Version: 1.1
Name: pyiridium9602
Version: 1.2.3
Summary: Python 3 iridium communication library for the iridium 9602 modem.
Home-page: https://github.com/justengel/pyiridium9602
Author: Justin Engel
Author-email: jengel@sealandaire.com
License: MIT
Download-URL: https://github.com/justengel/pyiridium9602/archive/v1.2.3.zip
Keywords: iridium 9602 iridium9602 serial
Platform: any
Classifier: Programming Language :: Python
Classifier: Programming Language :: Python :: 3
Classifier: Operating System :: OS Independent
